pyca.cpython-311-darwin.so
pyca_epics-3.3.3.dist-info/RECORD
pyca_epics-3.3.3.dist-info/WHEEL
pyca_epics-3.3.3.dist-info/top_level.txt
pyca_epics-3.3.3.dist-info/METADATA
pyca_epics-3.3.3.dist-info/licenses/LICENSE.md
pyca_epics-3.3.3.dist-info/licenses/AUTHORS.rst
psp/options.py
psp/version.py
psp/_version.py
psp/caput.py
psp/__init__.py
psp/Pv.py
psp/cainfo.py
psp/utils.py
psp/caget.py
psp/camonitor.py
psp/.dylibs/libca.7.0.7.99.1.dylib
psp/.dylibs/libCom.7.0.7.99.1.dylib
