Metadata-Version: 2.4
Name: pyca_epics
Version: 3.3.3
Summary: python channel access library
Author: SLAC National Accelerator Laboratory
License: Copyright (c) 2023, The Board of Trustees of the Leland Stanford Junior
Classifier: Development Status :: 2 - Pre-Alpha
Classifier: Natural Language :: English
Classifier: Programming Language :: Python :: 3
Requires-Python: >=3.9
License-File: LICENSE.md
License-File: AUTHORS.rst
Requires-Dist: epicscorelibs
Requires-Dist: numpy>1.23
Provides-Extra: test
Requires-Dist: pcaspy; extra == "test"
Requires-Dist: pytest; extra == "test"
Dynamic: license-file
